[
  {
    "schedule_metadata": {
      "state": "oh",
      "agency_name": "ELC",
      "schedule_type": "specific",
      "schedule_id": "50540002",
      "url": "https://rims.das.ohio.gov/Schedule/Details/18713"
    },
    "series_metadata": {
      "series_id": "ELC001",
      "series_title": "LITIGATION RECORDS",
      "series_description": "OHIO ELECTIONS COMMISSION CASES WHICH ARE APPEALED TO THE COMMON PLEAS COURT, OHIO SUPREME COURT OR THE UNITED STATES SUPREME COURT.",
      "legal_citation": null
    },
    "retention_rules": {
      "trigger_event": "Paper: MAINTAIN IN OFFICE LEGAL REFERENCE PERMANENTLY",
      "duration_years": 999,
      "duration_months": null,
      "disposition_method": "Paper: Permanent",
      "confidential_flag": false
    },
    "tracking_data": {
      "last_checked": "2026-03-30",
      "last_updated_by_state": "2003-01-13",
      "next_update_due": null,
      "comments": null
    },
    "state_specific_attributes": {
      "rsin": null
    }
  }
]