[
  {
    "schedule_metadata": {
      "state": "oh",
      "agency_name": "OBA",
      "schedule_type": "specific",
      "schedule_id": "970-0041",
      "url": "https://rims.das.ohio.gov/Schedule/Details/2242"
    },
    "series_metadata": {
      "series_id": "OBA-41",
      "series_title": "PERSONNEL RECORDS-FINANCIAL (ALL PROJECTS)",
      "series_description": "Personnel records - including pers. documentation for the OBA.",
      "legal_citation": null
    },
    "retention_rules": {
      "trigger_event": "Paper: in operating area one calendar year employment terminates. Continually maintain in storage",
      "duration_years": 999,
      "duration_months": null,
      "disposition_method": "Paper: Permanent",
      "confidential_flag": false
    },
    "tracking_data": {
      "last_checked": "2026-03-30",
      "last_updated_by_state": "1986-06-26",
      "next_update_due": null,
      "comments": null
    },
    "state_specific_attributes": {
      "rsin": null
    }
  }
]