[
  {
    "schedule_metadata": {
      "state": "oh",
      "agency_name": "OTC",
      "schedule_type": "specific",
      "schedule_id": "50580085",
      "url": "https://rims.das.ohio.gov/Schedule/Details/23485"
    },
    "series_metadata": {
      "series_id": "OTC-500-01",
      "series_title": "Comptroller''''''''s Monthly Traffic and Toll Audit Reports",
      "series_description": "A monthly file that contains the following traffic, revenue and toll audit reports generated by the computer: Traffic Density Report monthly year-to-date (prepared quarterly); Origin-Destination-Class reports (ODC)daily summary monthly detail and summary year-to-date (prepared quarterly); Tandem Trailer Combinations Report monthly yearly; Non-Revenue Report Summary monthly; Commonality Report monthly year-to-date (prepared quarterly); Interchange Comparative Report monthly; Charge Account History Listing yearly; Vendor Name & Address Listing yearly printout showing amounts paid to vendors; Open Accounts Receivable Register month-end; Charge Account Invoice Register semi-monthly.",
      "legal_citation": null
    },
    "retention_rules": {
      "trigger_event": "CR",
      "duration_years": 5,
      "duration_months": null,
      "disposition": "Electronic: Monthly reports retain for 5 years, Electronic: Trash",
      "confidential_flag": false
    },
    "tracking_data": {
      "last_checked": "2026-04-02",
      "last_updated_by_state": "2006-07-13",
      "next_update_due": null,
      "comments": null
    },
    "state_specific_attributes": {
      "rsin": null
    }
  }
]