[
  {
    "schedule_metadata": {
      "state": "oh",
      "agency_name": "OTC",
      "schedule_type": "specific",
      "schedule_id": "50580100",
      "url": "https://rims.das.ohio.gov/Schedule/Details/23644"
    },
    "series_metadata": {
      "series_id": "OTC-501-29",
      "series_title": "Inv 50 Inventory Issues Summary",
      "series_description": "Monthly computer generated report summarizing the cost of material used by account number.",
      "legal_citation": null
    },
    "retention_rules": {
      "trigger_event": "AV",
      "duration_years": null,
      "duration_months": null,
      "disposition": "Paper: No longer produced; discard, Paper: Recycle",
      "confidential_flag": false
    },
    "tracking_data": {
      "last_checked": "2026-04-02",
      "last_updated_by_state": "2006-07-19",
      "next_update_due": null,
      "comments": null
    },
    "state_specific_attributes": {
      "rsin": null
    }
  }
]