[
  {
    "schedule_metadata": {
      "state": "oh",
      "agency_name": "INS",
      "schedule_type": "specific",
      "schedule_id": "820-0746",
      "url": "https://rims.das.ohio.gov/Schedule/Details/25369"
    },
    "series_metadata": {
      "series_id": "130-10",
      "series_title": "Project Documentation",
      "series_description": "Information regarding current, on-going, and/or completed computer projects and assignments that documents problems and progress. Includes specifications for division computer projects.",
      "legal_citation": null
    },
    "retention_rules": {
      "trigger_event": "Paper: superseded, obsolete, or replaced ; Electronic: superseded, obsolete, or replaced",
      "duration_years": null,
      "duration_months": null,
      "disposition_method": "Paper: Wastepaper ; Electronic: Erase",
      "confidential_flag": false
    },
    "tracking_data": {
      "last_checked": "2026-03-30",
      "last_updated_by_state": "2007-10-15",
      "next_update_due": null,
      "comments": null
    },
    "state_specific_attributes": {
      "rsin": null
    }
  }
]