[
  {
    "schedule_metadata": {
      "state": "oh",
      "agency_name": "PUC",
      "schedule_type": "specific",
      "schedule_id": "870-0488",
      "url": "https://rims.das.ohio.gov/Schedule/Details/27248"
    },
    "series_metadata": {
      "series_id": "78.1",
      "series_title": "Inspection Reports and Compliance Reviews",
      "series_description": "Copies of hazardous materials inspections and supporting documentation. Copies of compliance reviews and supporting documentation (may include copies of NIF/NAV letters, requests for conferences, correspondence to/from respondents, settlement agreements.",
      "legal_citation": null
    },
    "retention_rules": {
      "trigger_event": "Paper: ; Electronic: case is closed and no further appeals can be filed",
      "duration_years": 5,
      "duration_months": null,
      "disposition_method": "Paper: Wastepaper ; Electronic: Delete",
      "confidential_flag": false
    },
    "tracking_data": {
      "last_checked": "2026-03-30",
      "last_updated_by_state": "2009-01-22",
      "next_update_due": null,
      "comments": null
    },
    "state_specific_attributes": {
      "rsin": null
    }
  }
]