[
  {
    "schedule_metadata": {
      "state": "oh",
      "agency_name": "INS",
      "schedule_type": "specific",
      "schedule_id": "820-0619",
      "url": "https://rims.das.ohio.gov/Schedule/Details/27980"
    },
    "series_metadata": {
      "series_id": "220-04",
      "series_title": "Independent Review Organization (IRO) Accreditation",
      "series_description": "Documents relating to accreditation of Independent Review Organizations (IROs). Includes initial and renewal applications and supporting documents, disposition documents (certificates, denials, revocations), and related correspondence. Authority: OAC 3901-8-04.",
      "legal_citation": null
    },
    "retention_rules": {
      "trigger_event": "AC",
      "duration_years": 2,
      "duration_months": null,
      "disposition": "Paper: Retain hard copy until imaged, then destroy hard copy. Initial Accreditation filing: Retain 2 years after inactive, then destroy. Renewal accreditation filing: Retain 3 years from the end of the applicable renewal year, then destroy. ; Electronic: Retain hard copy until imaged, then destroy hard copy. Initial Accreditation filing: Retain 2 years after inactive, then destroy. Renewal accreditation filing: Retain 3 years from the end of the applicable renewal year, then destroy., Paper: Recycle ; Electronic: Erase",
      "confidential_flag": false
    },
    "tracking_data": {
      "last_checked": "2026-04-02",
      "last_updated_by_state": "2009-09-18",
      "next_update_due": null,
      "comments": null
    },
    "state_specific_attributes": {
      "rsin": null
    }
  }
]