[
  {
    "schedule_metadata": {
      "state": "oh",
      "agency_name": "JFS",
      "schedule_type": "specific",
      "schedule_id": "795-0142",
      "url": "https://rims.das.ohio.gov/Schedule/Details/31039"
    },
    "series_metadata": {
      "series_id": "UC-CON-003",
      "series_title": "Reimbursing Negotiable Security and Surety Bond Files",
      "series_description": "File contains, but is not limited to, Reimbursing Employer Application, Treasurer of State receipts and release correspondence, inventory of securities with Treasurer of State, Reimbursing Employer Surety Bonds and related Continuation Certificates, Riders, Power of Attorney and related correspondence.",
      "legal_citation": null
    },
    "retention_rules": {
      "trigger_event": "Paper: in office 2. of inactivity subsequent effective discontinuance date and upon proper disposition of all debits and security instrument, image and certify ; Electronic: in System enterprise which account was established is no longer in operation and its account has not been chargeable a period of 7 years, and there are no outstanding debts",
      "duration_years": 5,
      "duration_months": null,
      "disposition_method": "Paper: Shred ; Electronic: Erase",
      "confidential_flag": false
    },
    "tracking_data": {
      "last_checked": "2026-03-30",
      "last_updated_by_state": "2013-02-15",
      "next_update_due": null,
      "comments": null
    },
    "state_specific_attributes": {
      "rsin": null
    }
  }
]