[
  {
    "schedule_metadata": {
      "state": "oh",
      "agency_name": "AGO",
      "schedule_type": "specific",
      "schedule_id": "10551553",
      "url": "https://rims.das.ohio.gov/Schedule/Details/32625"
    },
    "series_metadata": {
      "series_id": "86-OAG-51",
      "series_title": "Articles of Incorporation Review Files",
      "series_description": "ORC 1724.04 & 1726.03 require the AGO to review Articles of Incorporation, or amendments, pertaining to Community Improvement Corporations (ORC 1724.04), Development Corporations (ORC 1726.03), or County Land Reutilization Corporations (ORC 1724.04) to ensure consistency with state and federal laws. Files include, but are not limited to, correspondence from the Secretary of State (SOS) asking for AGO review, the article to be reviewed, amendments if applicable, and AGO findings letter to the SOS.",
      "legal_citation": null
    },
    "retention_rules": {
      "trigger_event": "CR",
      "trigger_desc": "Paper: scanned and saved document management system. ; Electronic",
      "duration_years": 5,
      "duration_months": null,
      "disposition_method": "Paper: Recycle ; Electronic: Delete",
      "confidential_flag": false
    },
    "tracking_data": {
      "last_checked": "2026-04-01",
      "last_updated_by_state": "2014-09-17",
      "next_update_due": null,
      "comments": null
    },
    "state_specific_attributes": {
      "rsin": null
    }
  }
]