[
  {
    "schedule_metadata": {
      "state": "oh",
      "agency_name": "CCC",
      "schedule_type": "specific",
      "schedule_id": "50670006",
      "url": "https://rims.das.ohio.gov/Schedule/Details/35986"
    },
    "series_metadata": {
      "series_id": "CCC-007",
      "series_title": "Denials/Revocations/Suspensions",
      "series_description": "This record series consists of applications and licenses that were denied, revoked, or suspended for failure to satisfy statutory or regulatory requirements for registration, licensure or certification, or for failure to comply with or maintain statutory or regulatory requirements.",
      "legal_citation": null
    },
    "retention_rules": {
      "trigger_event": "Paper: paper copy converted electronic format. Once electronic version verified as an accurate copy, shred paper copies. ; Electronic: three years following date of denial of application or when a license is deemed revoked or suspended, or expiration of applicant's or licensee's appeals, whichever is later",
      "duration_years": null,
      "duration_months": null,
      "disposition_method": "Paper: Shred ; Electronic: Erase",
      "confidential_flag": false
    },
    "tracking_data": {
      "last_checked": "2026-03-30",
      "last_updated_by_state": "2024-09-10",
      "next_update_due": null,
      "comments": null
    },
    "state_specific_attributes": {
      "rsin": null
    }
  }
]