[
  {
    "schedule_metadata": {
      "state": "oh",
      "agency_name": "DDD",
      "schedule_type": "specific",
      "schedule_id": "50740045",
      "url": "https://rims.das.ohio.gov/Schedule/Details/39159"
    },
    "series_metadata": {
      "series_id": "DDDITS-3",
      "series_title": "Security Affidavits",
      "series_description": "DODD Security Affidavits forms, which identify a particular DODD systems user and the level of access that user and/or entity has to each of the application systems. Required for each DODD employee and any external entity accessing DODD applications and is renewed either annually or according to the renewal schedule in ITS Policy ITS-001.",
      "legal_citation": null
    },
    "retention_rules": {
      "trigger_event": "AC",
      "duration_years": null,
      "duration_months": null,
      "disposition": "Paper: Retain until scanned and saved electronically or pursuant to the following: DODD Employees: Retain for one year after end of employment. Provider: Retain for seven years after end of certification with DODD. Billing entity: Retain for seven years after termination of relationships with all DODD providers. County Board employees: Retain for seven years after the end date of employment with the County Board. County Boards: Retain for seven years after termination of the relationship between the County Board and DODD. MAIS Nurse: Retain for seven years after the nurse's credentials have expired in MAIS. MAIS Secretaries: Retain for seven years after end of all relationships with MAIS nurses. ; Electronic: DODD Employee: Retain for one year after end of employment. Provider: Retain for seven years after end of certification with DODD. Billing entity: Retain for seven years after termination of relationships with all DODD providers. County Board employees: Retain for seven years after the end date of employment with the County Board. County Boards: Retain for seven years after termination of the relationship between the County Board and DODD. MAIS Nurse: Retain for seven years after the nurse's credentials have expired in MAIS. MAIS Secretaries: Retain for seven years after end of all relationships with MAIS nurses., Paper: Recycle ; Electronic: Delete",
      "confidential_flag": false
    },
    "tracking_data": {
      "last_checked": "2026-04-03",
      "last_updated_by_state": "2022-03-14",
      "next_update_due": null,
      "comments": null
    },
    "state_specific_attributes": {
      "rsin": null
    }
  }
]