[
  {
    "schedule_metadata": {
      "state": "oh",
      "agency_name": "ENG",
      "schedule_type": "specific",
      "schedule_id": "892-0045",
      "url": "https://rims.das.ohio.gov/Schedule/Details/8124"
    },
    "series_metadata": {
      "series_id": "INV-07",
      "series_title": "OTHER NCEE MEMBER BOARD INVESTGATIVE CORRESPONDENCE",
      "series_description": "Other NCEE member Board investigative correspondence related to committee reports.",
      "legal_citation": null
    },
    "retention_rules": {
      "trigger_event": "FE",
      "trigger_desc": "Paper: one year end of fiscal year in which initiated, and",
      "duration_years": null,
      "duration_months": null,
      "disposition_method": "Paper: Wastepaper",
      "confidential_flag": false
    },
    "tracking_data": {
      "last_checked": "2026-04-01",
      "last_updated_by_state": "1982-07-09",
      "next_update_due": null,
      "comments": null
    },
    "state_specific_attributes": {
      "rsin": null
    }
  }
]