[
  {
    "schedule_metadata": {
      "state": "oh",
      "agency_name": "DOT",
      "schedule_type": "specific",
      "schedule_id": "770-2633",
      "url": "https://rims.das.ohio.gov/Schedule/Details/36242"
    },
    "series_metadata": {
      "series_id": "TrafMgmt-7",
      "series_title": "Traffic Management Center Daily Logs",
      "series_description": "The TMC daily logs are the documentation of all communications regarding traffic incidents and requests for assistance at the ODOT Traffic Management Center.",
      "legal_citation": null
    },
    "retention_rules": {
      "trigger_event": "Electronic: current year five (5) years from date of incident",
      "duration_years": null,
      "duration_months": null,
      "disposition_method": "Electronic: Delete",
      "confidential_flag": false
    },
    "tracking_data": {
      "last_checked": "2026-03-31",
      "last_updated_by_state": "2019-04-09",
      "next_update_due": null,
      "comments": null
    },
    "state_specific_attributes": {
      "rsin": null
    }
  }
]