[
  {
    "schedule_metadata": {
      "state": "oh",
      "agency_name": "MED",
      "schedule_type": "specific",
      "schedule_id": "883-0168",
      "url": "https://rims.das.ohio.gov/Schedule/Details/35149"
    },
    "series_metadata": {
      "series_id": "REC-0016",
      "series_title": "Waivers of Continuing Medical Education Requirements",
      "series_description": "Request for waiver of CME requirements; copies of cover letters, etc.",
      "legal_citation": null
    },
    "retention_rules": {
      "trigger_event": "CR",
      "duration_years": 2,
      "duration_months": null,
      "disposition": "Paper: Retain until scanned to electronic medium for storage and scan is checked for accuracy; then destroy. If not scanned then retain for 2 years following the end of the renewal period to which the waiver request applied, then destroy ; Electronic: Retain for 2 years following the end of the renewal period to which the waiver request applied., Paper: Shred ; Electronic: Delete",
      "confidential_flag": false
    },
    "tracking_data": {
      "last_checked": "2026-04-02",
      "last_updated_by_state": "2021-12-06",
      "next_update_due": null,
      "comments": null
    },
    "state_specific_attributes": {
      "rsin": null
    }
  }
]