[
  {
    "schedule_metadata": {
      "state": "oh",
      "agency_name": "OTC",
      "schedule_type": "specific",
      "schedule_id": "50580115",
      "url": "https://rims.das.ohio.gov/Schedule/Details/23560"
    },
    "series_metadata": {
      "series_id": "OTC-500-73",
      "series_title": "Property Damage Invoices Not Billed",
      "series_description": "Invoices sent to Legal for review and recommendations not to bill the patron involved.",
      "legal_citation": null
    },
    "retention_rules": {
      "trigger_event": "CR",
      "duration_years": 3,
      "duration_months": null,
      "disposition": "Paper: Retain 3 years, Paper: Shred",
      "confidential_flag": false
    },
    "tracking_data": {
      "last_checked": "2026-04-03",
      "last_updated_by_state": "2006-08-16",
      "next_update_due": null,
      "comments": null
    },
    "state_specific_attributes": {
      "rsin": null
    }
  }
]