[
  {
    "schedule_metadata": {
      "state": "oh",
      "agency_name": "DRC",
      "schedule_type": "specific",
      "schedule_id": "15010244",
      "url": "https://rims.das.ohio.gov/Schedule/Details/20589"
    },
    "series_metadata": {
      "series_id": "LEG01",
      "series_title": "Federal Litigation",
      "series_description": "All files pertaining to complaints, petitions, writs, applications and appeals filed in federal district court, a federal court of appeals or the U.S. Supreme court where the Department and/or departmental employees are parties to the lawsuit.",
      "legal_citation": null
    },
    "retention_rules": {
      "trigger_event": "Paper: case is decided and appeals are exhausted",
      "duration_years": 5,
      "duration_months": null,
      "disposition_method": "Paper: Shred",
      "confidential_flag": false
    },
    "tracking_data": {
      "last_checked": "2026-03-31",
      "last_updated_by_state": "2004-05-26",
      "next_update_due": null,
      "comments": null
    },
    "state_specific_attributes": {
      "rsin": null
    }
  }
]