[
  {
    "schedule_metadata": {
      "state": "oh",
      "agency_name": "JFS",
      "schedule_type": "specific",
      "schedule_id": "400-0676",
      "url": "https://rims.das.ohio.gov/Schedule/Details/30977"
    },
    "series_metadata": {
      "series_id": "FIS-BCM-07",
      "series_title": "ODJFS Cost Allocation Expenditure Reports",
      "series_description": "Record includes worksheets, statistical information and rational for allocating administrative costs for the agency.",
      "legal_citation": null
    },
    "retention_rules": {
      "trigger_event": "CR",
      "duration_years": 3,
      "duration_months": null,
      "disposition": "Electronic: Retain in office 3 years and 4 years in the records center, then destroy provided audits have been completed and released, and all discrepancies have been resolved. ; Paper: Retain in office 3 years and 4 yearsin the records center, then destroyprovided audits have beencompleted and released, and alldiscrepancies have been resolved., Electronic: Erase ; Paper: Shred",
      "confidential_flag": false
    },
    "tracking_data": {
      "last_checked": "2026-04-03",
      "last_updated_by_state": "2024-07-02",
      "next_update_due": null,
      "comments": null
    },
    "state_specific_attributes": {
      "rsin": null
    }
  }
]