[
  {
    "schedule_metadata": {
      "state": "oh",
      "agency_name": "DAS",
      "schedule_type": "specific",
      "schedule_id": "100-1135",
      "url": "https://rims.das.ohio.gov/Schedule/Details/2446"
    },
    "series_metadata": {
      "series_id": "BO-FIS-11",
      "series_title": "Certificates of Participation",
      "series_description": "This series contains working papers dealing with negotiations; correspondence dealing with certificates of participation to and from using agencies and to and form Society Bank & Bank One (who are the trustees and are responsible for disbursement of funds). In order to buy equipment (computer & microwave) certificates are sold to raise money. Computer Services then pays the bank who in turn pays the certificate holders.",
      "legal_citation": null
    },
    "retention_rules": {
      "trigger_event": "Paper: five (5) years closeout of payment",
      "duration_years": null,
      "duration_months": null,
      "disposition_method": "Paper: Archives",
      "confidential_flag": false
    },
    "tracking_data": {
      "last_checked": "2026-03-31",
      "last_updated_by_state": "1995-04-20",
      "next_update_due": null,
      "comments": null
    },
    "state_specific_attributes": {
      "rsin": null
    }
  }
]