[
  {
    "schedule_metadata": {
      "state": "oh",
      "agency_name": "JFS",
      "schedule_type": "specific",
      "schedule_id": "6000132",
      "url": "https://rims.das.ohio.gov/Schedule/Details/31521"
    },
    "series_metadata": {
      "series_id": "EBS-CR-04",
      "series_title": "EEO Monitoring Reports",
      "series_description": "Reports written by enforcement officers when monitoring the ODJFS offices in the counties to ensure compliance with EEO guidelines. The reports include the number of clients served, staff and facility assessments, reviews of job applications and orders, comments and responses to the reports.",
      "legal_citation": null
    },
    "retention_rules": {
      "trigger_event": "Paper: in office and 3 years in records center ; Electronic: in office 5 years",
      "duration_years": 2,
      "duration_months": null,
      "disposition_method": "Paper: Shred ; Electronic: Erase",
      "confidential_flag": false
    },
    "tracking_data": {
      "last_checked": "2026-03-31",
      "last_updated_by_state": "2024-01-31",
      "next_update_due": null,
      "comments": null
    },
    "state_specific_attributes": {
      "rsin": null
    }
  }
]