[
  {
    "schedule_metadata": {
      "state": "oh",
      "agency_name": "FUN",
      "schedule_type": "specific",
      "schedule_id": "18810037",
      "url": "https://rims.das.ohio.gov/Schedule/Details/18358"
    },
    "series_metadata": {
      "series_id": "FUN-RN-001",
      "series_title": "License Renewal Application",
      "series_description": "This series contains license renewal applications, which contains licensees name, SS#, license number, address of licensee, and signature of licensee.",
      "legal_citation": null
    },
    "retention_rules": {
      "trigger_event": "CR",
      "trigger_desc": "Paper",
      "duration_years": 3,
      "duration_months": null,
      "disposition_method": "Paper: Wastepaper",
      "confidential_flag": false
    },
    "tracking_data": {
      "last_checked": "2026-04-01",
      "last_updated_by_state": "2002-10-22",
      "next_update_due": null,
      "comments": null
    },
    "state_specific_attributes": {
      "rsin": null
    }
  }
]