[
  {
    "schedule_metadata": {
      "state": "oh",
      "agency_name": "DRC",
      "schedule_type": "specific",
      "schedule_id": "501-0374",
      "url": "https://rims.das.ohio.gov/Schedule/Details/24195"
    },
    "series_metadata": {
      "series_id": "REC-0039",
      "series_title": "Bureau of Sentence Computation Legal File",
      "series_description": "An accurate and complete record pertaining to the calculation of an inmate''s sentence which includes copies of official court documents and any other related papers created to document the time an inmae is required to serve with the Department of Rehabilitation and Correction.",
      "legal_citation": null
    },
    "retention_rules": {
      "trigger_event": "Paper: ten years death, final release, maximum expiration or definite sentence expiration",
      "duration_years": null,
      "duration_months": null,
      "disposition_method": "Paper: Shred",
      "confidential_flag": false
    },
    "tracking_data": {
      "last_checked": "2026-03-31",
      "last_updated_by_state": "2006-11-02",
      "next_update_due": null,
      "comments": null
    },
    "state_specific_attributes": {
      "rsin": null
    }
  }
]