[
  {
    "schedule_metadata": {
      "state": "oh",
      "agency_name": "BWC",
      "schedule_type": "specific",
      "schedule_id": "855-1058",
      "url": "https://rims.das.ohio.gov/Schedule/Details/26476"
    },
    "series_metadata": {
      "series_id": "MIAD-50",
      "series_title": "Data Processing Disaster Preparedness and Recovery Plans",
      "series_description": "The Data Processing Disaster Preparedness and Recovery Plans are records related to the protection and reestablishment of data processing services, equipment and data (back-up files) in case of a disaster. The Data Processing Disaster Preparedness and Recovery Plans are stored offsite.",
      "legal_citation": null
    },
    "retention_rules": {
      "trigger_event": "US",
      "duration_years": null,
      "duration_months": null,
      "disposition": "Paper: Review twice a year in May and October when disaster recovery testing is performed, revise as needed and return to offsite storage at Fireproof. Retain until superseded by revised plan, and then destroy. ; Electronic: Review twice a year in May and October when disaster recovery testing is performed, revise as needed and return to offsite storage at Fireproof. Retain until superseded by revised plan, and then destroy., Paper: Shred ; Electronic: Delete",
      "confidential_flag": false
    },
    "tracking_data": {
      "last_checked": "2026-04-02",
      "last_updated_by_state": "2008-07-29",
      "next_update_due": null,
      "comments": null
    },
    "state_specific_attributes": {
      "rsin": null
    }
  }
]