[
  {
    "schedule_metadata": {
      "state": "oh",
      "agency_name": "COM",
      "schedule_type": "specific",
      "schedule_id": "800-0211",
      "url": "https://rims.das.ohio.gov/Schedule/Details/26890"
    },
    "series_metadata": {
      "series_id": "64-13",
      "series_title": "Withdrawn Applications (Dealer, Sales, Property)",
      "series_description": "This file consists of applications for licensure and/or qualification of property which are withdrawn at the request of the applicant. File consist of soc sec. #.",
      "legal_citation": null
    },
    "retention_rules": {
      "trigger_event": "Paper: in office 30 days initial request withdraw is received",
      "duration_years": null,
      "duration_months": null,
      "disposition_method": "Paper: Shred",
      "confidential_flag": false
    },
    "tracking_data": {
      "last_checked": "2026-03-31",
      "last_updated_by_state": "2008-11-10",
      "next_update_due": null,
      "comments": null
    },
    "state_specific_attributes": {
      "rsin": null
    }
  }
]