[
  {
    "schedule_metadata": {
      "state": "oh",
      "agency_name": "AGR",
      "schedule_type": "specific",
      "schedule_id": "700-0016",
      "url": "https://rims.das.ohio.gov/Schedule/Details/38646"
    },
    "series_metadata": {
      "series_id": "AGR-2003",
      "series_title": "Frozen Food Establishment License and Applications",
      "series_description": "License and application for frozen food establishments.",
      "legal_citation": null
    },
    "retention_rules": {
      "trigger_event": "AV",
      "duration_years": null,
      "duration_months": null,
      "disposition": "Paper: Two year retention period then destroy provided audited by the state auditor, Paper: Wastepaper",
      "confidential_flag": false
    },
    "tracking_data": {
      "last_checked": "2026-04-03",
      "last_updated_by_state": "2020-01-23",
      "next_update_due": null,
      "comments": null
    },
    "state_specific_attributes": {
      "rsin": null
    }
  }
]