[
  {
    "schedule_metadata": {
      "state": "oh",
      "agency_name": "DCY",
      "schedule_type": "specific",
      "schedule_id": "50930045",
      "url": "https://rims.das.ohio.gov/Schedule/Details/39783"
    },
    "series_metadata": {
      "series_id": "DCY-ICPC",
      "series_title": "Interstate Compact for the Placement of Children",
      "series_description": "Records pertaining to the placement of children within and outside the State of Ohio for adoption, foster care or residential treatment. Case files include: Interstate Compact Placement Request 100-A (JFS01661); Interstate Compact Placement Report on Child’s Placement Status 100-B(JFS 01662); Interstate Compact Transmittal (JFS 01640); Statement of Assurance(ODHS 1674); and Social and Medical History\u0002Biological Mother and Father(ODHS 1616) BCII, FBI Central Registry, references, psychological, JFS 1653Medical statements and all other home study documents.",
      "legal_citation": null
    },
    "retention_rules": {
      "trigger_event": "PM",
      "trigger_desc": "Paper: 60 days hardcopy is prepped, scanned, indexed (imaged)and quality control is complete ; Electronic: microfilm or CD in office permanently",
      "duration_years": 999,
      "duration_months": null,
      "disposition_method": "Paper: Shred ; Electronic: Permanent",
      "confidential_flag": false
    },
    "tracking_data": {
      "last_checked": "2026-04-01",
      "last_updated_by_state": "2025-06-02",
      "next_update_due": null,
      "comments": null
    },
    "state_specific_attributes": {
      "rsin": null
    }
  }
]