[
  {
    "agency_name": null,
    "state": "va",
    "schedule_type": "specific",
    "schedule_id": "601-017",
    "series_id": "009506",
    "series_title": "Medical Examiner's (ME) Records",
    "series_description": "This series documents a death. This series may include, but autopsy report, toxicology report, evidence receipt, personal effects unknown body, cremation child death investigation form, and",
    "retention_statement": "event",
    "retention_years": null,
    "retention_code": "",
    "comments": "",
    "disposition": "Confidential Destruction",
    "confidential": true,
    "legal_citation": "",
    "last_checked": "2026-02-26",
    "last_updated": null,
    "next_update": ""
  },
  {
    "agency_name": null,
    "state": "va",
    "schedule_type": "specific",
    "schedule_id": "601-017",
    "series_id": "009507",
    "series_title": "Morgue Log Books",
    "series_description": "This series documents log in/out that are brought into the morgue. not limited to: decedent's name, home, and date and time decedent from the ME's facility.",
    "retention_statement": "",
    "retention_years": null,
    "retention_code": "",
    "comments": "",
    "disposition": "Permanent, In Agency",
    "confidential": false,
    "legal_citation": "",
    "last_checked": "2026-02-26",
    "last_updated": null,
    "next_update": ""
  },
  {
    "agency_name": null,
    "state": "va",
    "schedule_type": "specific",
    "schedule_id": "601-017",
    "series_id": "200841",
    "series_title": "Turndowns",
    "series_description": "This series documents information not fall under the jurisdiction of the series may include, but is not enforcement agency reports, prescription monitoring records, certificates, and correspondence.",
    "retention_statement": "notification",
    "retention_years": null,
    "retention_code": "",
    "comments": "",
    "disposition": "Confidential Destruction",
    "confidential": true,
    "legal_citation": "",
    "last_checked": "2026-02-26",
    "last_updated": null,
    "next_update": ""
  },
  {
    "agency_name": null,
    "state": "va",
    "schedule_type": "specific",
    "schedule_id": "601-017",
    "series_id": "001015",
    "series_title": "Virginia State Anatomical Program",
    "series_description": "This series documents the donation advancement at medical schools Virginia. This series may include, records, transportation reports.",
    "retention_statement": "last action",
    "retention_years": null,
    "retention_code": "",
    "comments": "",
    "disposition": "Confidential Destruction",
    "confidential": true,
    "legal_citation": "",
    "last_checked": "2026-02-26",
    "last_updated": null,
    "next_update": ""
  }
]